reactpy_router/__init__.py
reactpy_router/components.py
reactpy_router/converters.py
reactpy_router/hooks.py
reactpy_router/py.typed
reactpy_router/resolvers.py
reactpy_router/routers.py
reactpy_router/types.py
reactpy_router/static/bundle.js
reactpy_router-2.0.0.dist-info/METADATA
reactpy_router-2.0.0.dist-info/WHEEL
reactpy_router-2.0.0.dist-info/licenses/LICENSE.md
reactpy_router-2.0.0.dist-info/RECORD
