Metadata-Version: 2.4
Name: reactpy_router
Version: 2.0.0
Summary: A URL router for ReactPy.
Project-URL: Changelog, https://reactive-python.github.io/reactpy-router/latest/about/changelog/
Project-URL: Documentation, https://reactive-python.github.io/reactpy-router/latest/
Project-URL: Source, https://github.com/reactive-python/reactpy-router
Author-email: Mark Bakhit <archiethemonger@gmail.com>
License-Expression: MIT
License-File: LICENSE.md
Keywords: React,ReactJS,ReactPy,components
Classifier: Environment :: Web Environment
Classifier: Intended Audience :: Developers
Classifier: Intended Audience :: Science/Research
Classifier: Operating System :: OS Independent
Classifier: Programming Language :: Python :: 3.9
Classifier: Programming Language :: Python :: 3.10
Classifier: Programming Language :: Python :: 3.11
Classifier: Programming Language :: Python :: 3.12
Classifier: Topic :: Multimedia :: Graphics
Classifier: Topic :: Software Development :: User Interfaces
Classifier: Topic :: Software Development :: Widget Sets
Classifier: Typing :: Typed
Requires-Python: >=3.9
Requires-Dist: reactpy<2.0.0,>=1.1.0
Requires-Dist: typing-extensions
